omSipCreator/__init__.py
omSipCreator/__init__.pyc
omSipCreator/__main__.py
omSipCreator/batch.py
omSipCreator/byteconv.py
omSipCreator/carrier.py
omSipCreator/cdinfo.py
omSipCreator/checksums.py
omSipCreator/config.py
omSipCreator/config.pyc
omSipCreator/mdaudio.py
omSipCreator/mods.py
omSipCreator/mods.pyc
omSipCreator/omSipCreator.py
omSipCreator/omSipCreator.pyc
omSipCreator/ppn.py
omSipCreator/premis.py
omSipCreator/shared.py
omSipCreator/kbapi/__init__.py
omSipCreator/kbapi/sru.py
omSipCreator/tools/mediainfo/History.txt
omSipCreator/tools/mediainfo/LIBCURL.DLL
omSipCreator/tools/mediainfo/License.html
omSipCreator/tools/mediainfo/MediaInfo.exe
omSipCreator/tools/mediainfo/ReadMe.txt
omSipCreator/tools/mediainfo/Plugin/Custom/Example.csv
omSipCreator/tools/mediainfo/Plugin/Custom/Example_HTML.csv
"omSipCreator/tools/mediainfo/Plugin/Custom/Table by fields, compact (HTML).csv"
"omSipCreator/tools/mediainfo/Plugin/Custom/Table by fields, short (HTML).csv"
"omSipCreator/tools/mediainfo/Plugin/Custom/Table by fields, standard (HTML).csv"
"omSipCreator/tools/mediainfo/Plugin/Custom/Table by fields, verbose (HTML).csv"
"omSipCreator/tools/mediainfo/Plugin/Custom/Table by streams, compact (HTML).csv"
"omSipCreator/tools/mediainfo/Plugin/Custom/Table by streams, short (HTML).csv"
"omSipCreator/tools/mediainfo/Plugin/Custom/Table by streams, standard (HTML).csv"
"omSipCreator/tools/mediainfo/Plugin/Custom/Table by streams, verbose (HTML).csv"
omSipCreator/tools/mediainfo/Plugin/Custom/XML.csv
omSipCreator/tools/mediainfo/Plugin/Custom/en.Example.csv
omSipCreator/tools/mediainfo/Plugin/Custom/en.Example_HTML.csv
omSipCreator/tools/mediainfo/Plugin/Custom/fr.Example.csv
omSipCreator/tools/mediainfo/Plugin/Custom/it.Esempio.csv
omSipCreator/tools/mediainfo/Plugin/Custom/it.Esempio_HTML.csv
omSipCreator/tools/mediainfo/Plugin/Custom/zzz_Contrib - Dusil (HTML).csv
omSipCreator-0.8.0.dist-info/LICENSE
omSipCreator-0.8.0.dist-info/METADATA
omSipCreator-0.8.0.dist-info/WHEEL
omSipCreator-0.8.0.dist-info/entry_points.txt
omSipCreator-0.8.0.dist-info/top_level.txt
omSipCreator-0.8.0.dist-info/RECORD
