Metadata-Version: 2.1
Name: omSipCreator
Version: 0.8.0
Summary: Create ingest-ready SIPs from batches of optical media images
Home-page: https://github.com/KBNLresearch/omSipCreator
Author: Johan van der Knijff
Author-email: johan.vanderknijff@kb.nl
Maintainer: Johan van der Knijff
Maintainer-email: johan.vanderknijff@kb.nl
License: Apache License 2.0
Download-URL: https://github.com/KBNLresearch/omSipCreator/archive/0.8.0.tar.gz
Platform: POSIX
Platform: Windows
Classifier: Environment :: Console
Classifier: Programming Language :: Python :: 3
Requires-Python: >=3.2
Requires-Dist: requests
Requires-Dist: setuptools
Requires-Dist: lxml
Requires-Dist: pytz
Requires-Dist: isolyzer
